decol/__init__.py
decol/_version.py
decol/cli.py
decol/csv.py
decol/util.py
decol-1.1.7.dist-info/LICENSE.txt
decol-1.1.7.dist-info/METADATA
decol-1.1.7.dist-info/RECORD
decol-1.1.7.dist-info/WHEEL
decol-1.1.7.dist-info/entry_points.txt
decol-1.1.7.dist-info/top_level.txt
