Metadata-Version: 2.1
Name: decol
Version: 1.1.7
Summary: A tool to drop or keep columns from a CSV file.
Home-page: https://github.com/ctberthiaume/decol
Author: Chris T. Berthiaume
Author-email: chrisbee@uw.edu
License: MIT
Download-URL: https://github.com/ctberthiaume/decol/archive/1.1.7.tar.gz
Keywords: csv,command-line
Platform: any
Classifier: Development Status :: 3 - Alpha
Classifier: Intended Audience :: Developers
Classifier: Topic :: Utilities
Classifier: License :: OSI Approved :: MIT License
Classifier: Programming Language :: Python :: 2
Classifier: Programming Language :: Python :: 2.7
Classifier: Programming Language :: Python :: 3
Requires-Python: >=2.6, <4
Requires-Dist: click
